LICENSE
README.md
setup.py
CovRegpy/CovRegpy.py
CovRegpy/CovRegpy_DCC.py
CovRegpy/CovRegpy_RPP.py
CovRegpy/CovRegpy_SSA.py
CovRegpy/CovRegpy_SSD.py
CovRegpy/CovRegpy_X11.py
CovRegpy/__init__.py
CovRegpy.egg-info/PKG-INFO
CovRegpy.egg-info/SOURCES.txt
CovRegpy.egg-info/dependency_links.txt
CovRegpy.egg-info/requires.txt
CovRegpy.egg-info/top_level.txt